d_vecdb_server/__init__.py
d_vecdb_server/cli.py
d_vecdb_server/server.py
d_vecdb_server/binaries/vectordb-server
d_vecdb_server-0.1.2.dist-info/METADATA
d_vecdb_server-0.1.2.dist-info/WHEEL
d_vecdb_server-0.1.2.dist-info/entry_points.txt
d_vecdb_server-0.1.2.dist-info/top_level.txt
d_vecdb_server-0.1.2.dist-info/RECORD
