Metadata-Version: 2.4
Name: d-vecdb-server
Version: 0.1.2
Summary: Complete d-vecDB server package with embedded binaries - zero configuration required
Home-page: https://github.com/rdmurugan/d-vecDB
Author: Durai
Author-email: Durai <durai@infinidatum.com>
License: MIT
Project-URL: Homepage, https://github.com/rdmurugan/d-vecDB
Project-URL: Bug Reports, https://github.com/rdmurugan/d-vecDB/issues
Project-URL: Source, https://github.com/rdmurugan/d-vecDB
Project-URL: Documentation, https://github.com/rdmurugan/d-vecDB#readme
Keywords: vector database,similarity search,machine learning,embeddings,rust
Classifier: Development Status :: 4 - Beta
Classifier: Intended Audience :: Developers
Classifier: Intended Audience :: Science/Research
Classifier: License :: OSI Approved :: MIT License
Classifier: Operating System :: OS Independent
Classifier: Programming Language :: Python :: 3
Classifier: Programming Language :: Python :: 3.8
Classifier: Programming Language :: Python :: 3.9
Classifier: Programming Language :: Python :: 3.10
Classifier: Programming Language :: Python :: 3.11
Classifier: Programming Language :: Python :: 3.12
Classifier: Topic :: Database
Classifier: Topic :: Scientific/Engineering :: Artificial Intelligence
Requires-Python: >=3.8
Requires-Dist: requests>=2.25.0
Provides-Extra: client
Requires-Dist: d-vecdb; extra == "client"
Provides-Extra: dev
Requires-Dist: pytest>=7.0.0; extra == "dev"
Requires-Dist: black>=22.0.0; extra == "dev"
Requires-Dist: isort>=5.0.0; extra == "dev"
Dynamic: author
Dynamic: home-page
Dynamic: requires-python
